MANIFEST.in
README.rst
setup.cfg
setup.py
googleplusauth/__init__.py
googleplusauth/bootstrap.py
googleplusauth/helpers.py
googleplusauth/partials.py
googleplusauth/controllers/__init__.py
googleplusauth/controllers/root.py
googleplusauth/i18n/it/LC_MESSAGES/googleplusauth.mo
googleplusauth/lib/__init__.py
googleplusauth/lib/utils.py
googleplusauth/migration/env.py
googleplusauth/migration/script.py.mako
googleplusauth/migration/versions/c69f3a6d8bea_add_to_already_existing_app.py
googleplusauth/migration/versions/empty.txt
googleplusauth/model/__init__.py
googleplusauth/model/ming_models.py
googleplusauth/model/sqla_models.py
googleplusauth/public/__init__.py
googleplusauth/public/css/style.css
googleplusauth/public/images/star.png
googleplusauth/templates/__init__.py
googleplusauth/templates/little_partial.html
tgapp_googlePlusAuth.egg-info/PKG-INFO
tgapp_googlePlusAuth.egg-info/SOURCES.txt
tgapp_googlePlusAuth.egg-info/dependency_links.txt
tgapp_googlePlusAuth.egg-info/entry_points.txt
tgapp_googlePlusAuth.egg-info/not-zip-safe
tgapp_googlePlusAuth.egg-info/requires.txt
tgapp_googlePlusAuth.egg-info/top_level.txt