Metadata-Version: 1.0
Name: tgapp-googlePlusAuth
Version: 0.0.9
Summary: Google Authentication for TurboGears2
Home-page: https://github.com/axant/tgapp-googleplusauth
Author: AXANT
Author-email: tech@axant.it
License: UNKNOWN
Keywords: turbogears2.application
Platform: UNKNOWN
